maxcutpy/__init__.py
maxcutpy/mcmanager.py
maxcutpy/rtr/__init__.py
maxcutpy/rtr/_rtr.py
maxcutpy/rtr/_tcg.py
maxcutpy/rtr/stiefel/__init__.py
maxcutpy/rtr/stiefel/_stiefel.py
maxcutpy/solvers/__init__.py
maxcutpy/solvers/abstractmaxcut.py
maxcutpy/solvers/bmmaxcut.py
maxcutpy/solvers/cemaxcut.py
maxcutpy/solvers/randommaxcut.py
maxcutpy-0.1.2.dist-info/LICENSE
maxcutpy-0.1.2.dist-info/WHEEL
maxcutpy-0.1.2.dist-info/METADATA
maxcutpy-0.1.2.dist-info/RECORD
